DESCRIPTION.rst
MANIFEST.in
README.md
setup.py
pubkey/__init__.py
pubkey/pubkey
pubkey.egg-info/PKG-INFO
pubkey.egg-info/SOURCES.txt
pubkey.egg-info/dependency_links.txt
pubkey.egg-info/requires.txt
pubkey.egg-info/top_level.txt