Metadata-Version: 1.1
Name: pubkey
Version: 0.9.6
Summary: Public Key Distribution made simple.
Home-page: https://github.com/fxstein/pubkey
Author: Oliver Ratzesberger <https://github.com/fxstein>
Author-email: Oliver(dot)Ratzesberger(at)gmail(dot)com
License: MIT
Keywords: public private keys pairs security ssh rest asyncio cement
Platform: UNKNOWN
Classifier: Development Status :: 4 - Beta
Classifier: Intended Audience :: Developers
Classifier: Intended Audience :: System Administrators
Classifier: Topic :: System :: Systems Administration
Classifier: Topic :: Security :: Cryptography
Classifier: License :: OSI Approved :: MIT License
Classifier: Programming Language :: Python :: 3
Classifier: Programming Language :: Python :: 3.4
Classifier: Programming Language :: Python :: 3.5
Classifier: Programming Language :: Python :: 3 :: Only
